vaitool/__init__.py
vaitool/bdd_to_vai.py
vaitool/coco_to_vai.py
vaitool/vai_to_bdd.py
vaitool/vai_to_coco.py
vaitool/schemas/__init__.py
vaitool/schemas/bdd_schema.py
vaitool/schemas/coco_schema.py
vaitool/schemas/visionai_schema.py
vaitool/utils/__init__.py
vaitool/utils/calculation.py
vaitool/utils/classes.py
vaitool/utils/common.py
vaitool/utils/converter.py
vaitool/utils/resize.py
vaitool/utils/validator.py
vaitool-0.0.0.4b1.dist-info/METADATA
vaitool-0.0.0.4b1.dist-info/WHEEL
vaitool-0.0.0.4b1.dist-info/top_level.txt
vaitool-0.0.0.4b1.dist-info/RECORD
