Metadata-Version: 2.1
Name: vaitool
Version: 0.0.0.4b1
Summary: converter tool for visionai format
Home-page: 
Author: LinkerNetworks
Requires-Python: >=3.9, <4
Requires-Dist: pydantic
